{
  "Type": 3,
  "Index": 1,
  "TagIndex": 0,
  "LayerIndex": 0,
  "StaticIndex": 0,
  "GameObjectData": {
    "Index": 1,
    "Name": "NavMesh",
    "Tag": "Default",
    "Layer": 0,
    "StaticType": 0,
    "Transform": {
      "Position": {
        "X": 0.0,
        "Y": 0.0,
        "Z": 0.0
      },
      "Rotation": {
        "X": 0.0,
        "Y": 0.0,
        "Z": 0.0
      },
      "Scale": {
        "X": 1.0,
        "Y": 1.0,
        "Z": 1.0
      }
    }
  },
  "MeshData": {
    "Index": 1,
    "MeshFilePath": "",
    "DiffuseTexturePath": ""
  },
  "MapData": {
    "Index": 1,
    "Group": 0
  },
  "NavMeshData": {
    "Index": 1,
    "CellCount": 2
  },
  "Cell_0": {
    "CellIndex": 3,
    "PositionX": 8,
    "PositionY": 8,
    "PositionZ": 17,
    "Option": 0,
    "Group": 100
  },
  "Cell_1": {
    "CellIndex": 4,
    "PositionX": 29,
    "PositionY": 23,
    "PositionZ": 6,
    "Option": 0,
    "Group": 100
  }
}